MANIFEST.in
README.rst
setup.cfg
setup.py
setup_helpers.py
template.py
flufl/__init__.py
flufl.password.egg-info/PKG-INFO
flufl.password.egg-info/SOURCES.txt
flufl.password.egg-info/dependency_links.txt
flufl.password.egg-info/namespace_packages.txt
flufl.password.egg-info/top_level.txt
flufl/password/NEWS.rst
flufl/password/README.rst
flufl/password/__init__.py
flufl/password/_generate.py
flufl/password/_hash.py
flufl/password/_registry.py
flufl/password/_utils.py
flufl/password/_verify.py
flufl/password/conf.py
flufl/password/schemes.py
flufl/password/docs/__init__.py
flufl/password/docs/using.rst
flufl/password/tests/__init__.py
flufl/password/tests/test_documentation.py
flufl/password/tests/test_passwords.py