Metadata-Version: 1.1
Name: flufl.password
Version: 1.3
Summary: Password hashing and verification.
Home-page: http://launchpad.net/flufl.password
Author: Barry Warsaw
Author-email: barry@python.org
License: LGPLv3
Download-URL: https://launchpad.net/flufl.password/+download
Platform: UNKNOWN
Classifier: Development Status :: 5 - Production/Stable
Classifier: Intended Audience :: Developers
Classifier: License :: OSI Approved :: GNU Lesser General Public License v3 or later (LGPLv3+)
Classifier: Operating System :: POSIX
Classifier: Operating System :: Microsoft :: Windows
Classifier: Operating System :: MacOS :: MacOS X
Classifier: Programming Language :: Python
Classifier: Programming Language :: Python :: 2.6
Classifier: Programming Language :: Python :: 2.7
Classifier: Programming Language :: Python :: 3
Classifier: Topic :: Software Development :: Libraries
Classifier: Topic :: Software Development :: Libraries :: Python Modules
